epitaxy-0.1.0.dist-info/METADATA
epitaxy-0.1.0.dist-info/WHEEL
epitaxy-0.1.0.dist-info/entry_points.txt
epitaxy-0.1.0.dist-info/licenses/LICENSE
epitaxy/__init__.py
epitaxy/__main__.py
epitaxy/filter.py
epitaxy/main.py
epitaxy/py.typed
epitaxy/utilities.py
epitaxy-0.1.0.dist-info/RECORD
