Metadata-Version: 2.1
Name: epitaxy
Version: 0.1.0
Summary: codebase consolidation tool
Author: OLILHR
License:                     GNU GENERAL PUBLIC LICENSE
Classifier: Development Status :: 4 - Beta
Classifier: Environment :: Console
Classifier: Intended Audience :: Developers
Classifier: License :: OSI Approved :: GNU General Public License v3 (GPLv3)
Classifier: Operating System :: OS Independent
Classifier: Programming Language :: Python
Classifier: Programming Language :: Python :: 3 :: Only
Classifier: Programming Language :: Python :: 3.12
Classifier: Topic :: Software Development :: Libraries :: Python Modules
Project-URL: Changelog, https://github.com/OLILHR/epitaxy/releases
Project-URL: Homepage, https://github.com/OLILHR/epitaxy
Requires-Python: >=3.12
Requires-Dist: click>=8.1.7
Requires-Dist: prompt_toolkit>=3.0.47
Requires-Dist: tiktoken>=0.7.0
Requires-Dist: tqdm>=4.66.5
Requires-Dist: types-tqdm>=4.66.0
